adbeasykey/README.MD
adbeasykey/__init__.py
adbeasykey/requirements.txt
adbeasykey/thirdparty.json
adbeasykey-0.12.dist-info/LICENSE.rst
adbeasykey-0.12.dist-info/METADATA
adbeasykey-0.12.dist-info/WHEEL
adbeasykey-0.12.dist-info/top_level.txt
adbeasykey-0.12.dist-info/RECORD
