Metadata-Version: 2.1
Name: adbeasykey
Version: 0.12
Summary: handles spaces, accents and other sneaky characters in ADB commands
Home-page: https://github.com/hansalemaos/adbeasykey
Author: Johannes Fischer
Author-email: aulasparticularesdealemaosp@gmail.com
License: MIT
Keywords: adb,android,keyevent,input text
Classifier: Development Status :: 4 - Beta
Classifier: Programming Language :: Python :: 3 :: Only
Classifier: Programming Language :: Python :: 3.10
Classifier: Topic :: Software Development :: Libraries :: Python Modules
Classifier: Topic :: Utilities
License-File: LICENSE.rst
Requires-Dist: detachedproc
Requires-Dist: fullpath83replace
Requires-Dist: kthread
Requires-Dist: kthread-sleep
Requires-Dist: normaltext
Requires-Dist: punktdict
Requires-Dist: requests
